odoo/addons/loyalty_card_fixed_expiration_date/README.rst
odoo/addons/loyalty_card_fixed_expiration_date/__init__.py
odoo/addons/loyalty_card_fixed_expiration_date/__manifest__.py
odoo/addons/loyalty_card_fixed_expiration_date/i18n/ca.po
odoo/addons/loyalty_card_fixed_expiration_date/i18n/es.po
odoo/addons/loyalty_card_fixed_expiration_date/i18n/it.po
odoo/addons/loyalty_card_fixed_expiration_date/i18n/loyalty_card_fixed_expiration_date.pot
odoo/addons/loyalty_card_fixed_expiration_date/models/__init__.py
odoo/addons/loyalty_card_fixed_expiration_date/models/loyalty_card.py
odoo/addons/loyalty_card_fixed_expiration_date/models/loyalty_program.py
odoo/addons/loyalty_card_fixed_expiration_date/readme/CONTRIBUTORS.md
odoo/addons/loyalty_card_fixed_expiration_date/readme/DESCRIPTION.md
odoo/addons/loyalty_card_fixed_expiration_date/readme/USAGE.md
odoo/addons/loyalty_card_fixed_expiration_date/static/description/icon.png
odoo/addons/loyalty_card_fixed_expiration_date/static/description/index.html
odoo/addons/loyalty_card_fixed_expiration_date/tests/__init__.py
odoo/addons/loyalty_card_fixed_expiration_date/tests/test_loyalty_card.py
odoo/addons/loyalty_card_fixed_expiration_date/views/loyalty_program_views.xml
odoo_addon_loyalty_card_fixed_expiration_date-17.0.1.0.0.4.dist-info/METADATA
odoo_addon_loyalty_card_fixed_expiration_date-17.0.1.0.0.4.dist-info/WHEEL
odoo_addon_loyalty_card_fixed_expiration_date-17.0.1.0.0.4.dist-info/top_level.txt
odoo_addon_loyalty_card_fixed_expiration_date-17.0.1.0.0.4.dist-info/RECORD
