Metadata-Version: 2.1
Name: odoo-addon-loyalty_card_fixed_expiration_date
Version: 17.0.1.0.0.4
Requires-Python: >=3.10
Requires-Dist: odoo>=17.0a,<17.1dev
Summary: Set a fixed expiration date for loyalty cards
Home-page: https://github.com/OCA/sale-promotion
License: AGPL-3
Author: (APSL-Nagarro), Odoo Community Association (OCA)
Author-email: support@odoo-community.org
Classifier: Programming Language :: Python
Classifier: Framework :: Odoo
Classifier: Framework :: Odoo :: 17.0
Classifier: License :: OSI Approved :: GNU Affero General Public License v3
